sauceclient.py
sauceclient-1.0.1.dist-info/licenses/LICENSE
sauceclient-1.0.1.dist-info/METADATA
sauceclient-1.0.1.dist-info/WHEEL
sauceclient-1.0.1.dist-info/top_level.txt
sauceclient-1.0.1.dist-info/RECORD
