Metadata-Version: 2.4
Name: sauceclient
Version: 1.0.1
Summary: Python client library for Sauce Labs API
Author: Corey Goldberg
Maintainer: Corey Goldberg
License-Expression: Apache-2.0
Project-URL: homepage, https://github.com/cgoldberg/sauceclient
Project-URL: source, https://github.com/cgoldberg/sauceclient
Project-URL: download, https://pypi.org/project/sauceclient
Keywords: API,Cloud,Testing,Sauce Labs
Classifier: Intended Audience :: Developers
Classifier: Operating System :: OS Independent
Classifier: Programming Language :: Python
Classifier: Programming Language :: Python :: 3
Classifier: Programming Language :: Python :: 3.9
Classifier: Programming Language :: Python :: 3.10
Classifier: Programming Language :: Python :: 3.11
Classifier: Programming Language :: Python :: 3.12
Classifier: Programming Language :: Python :: 3.13
Classifier: Topic :: Software Development :: Libraries :: Python Modules
Classifier: Topic :: Software Development :: Testing
Requires-Python: >=3.9
License-File: LICENSE
Dynamic: license-file
